Exodushcat.py
exodushcat-1.0.dist-info/LICENSE
exodushcat-1.0.dist-info/METADATA
exodushcat-1.0.dist-info/WHEEL
exodushcat-1.0.dist-info/RECORD
